[
    {
        "statementID": "openownership-register-7093687007106811753",
        "statementType": "entityStatement",
        "entityType": "registeredEntity",
        "name": "INFORMATION AND DATA NETWORKS SUPPLIES LIMITED",
        "incorporatedInJurisdiction": {
            "name": "United Kingdom of Great Britain and Northern Ireland",
            "code": "GB"
        },
        "identifiers": [
            {
                "scheme": "GB-COH",
                "schemeName": "Companies House",
                "id": "02248449"
            },
            {
                "schemeName": "OpenCorporates",
                "id": "https://opencorporates.com/companies/gb/02248449",
                "uri": "https://opencorporates.com/companies/gb/02248449"
            },
            {
                "schemeName": "OpenOwnership Register",
                "id": "http://register.openownership.org/entities/59b95a8e67e4ebf340f09d00",
                "uri": "http://register.openownership.org/entities/59b95a8e67e4ebf340f09d00"
            }
        ],
        "foundingDate": "1988-04-26",
        "addresses": [
            {
                "type": "registered",
                "address": "1b Springfield Court, Summerfield Road, Bolton, Lancs, BL3 2NT",
                "country": "GB"
            }
        ]
    },
    {
        "statementID": "openownership-register-7021517678293660192",
        "statementType": "ownershipOrControlStatement",
        "statementDate": "2016-04-06",
        "subject": {
            "describedByEntityStatement": "openownership-register-7093687007106811753"
        },
        "interestedParty": {
            "describedByEntityStatement": "openownership-register-17401368257004616614"
        },
        "interests": [
            {
                "type": "shareholding",
                "details": "ownership-of-shares-75-to-100-percent",
                "share": {
                    "minimum": 75,
                    "maximum": 100,
                    "exclusiveMinimum": false,
                    "exclusiveMaximum": false
                },
                "startDate": "2016-04-06"
            },
            {
                "type": "voting-rights",
                "details": "voting-rights-75-to-100-percent",
                "share": {
                    "minimum": 75,
                    "maximum": 100,
                    "exclusiveMinimum": false,
                    "exclusiveMaximum": false
                },
                "startDate": "2016-04-06"
            },
            {
                "type": "appointment-of-board",
                "details": "right-to-appoint-and-remove-directors",
                "startDate": "2016-04-06"
            }
        ],
        "source": {
            "type": [
                "officialRegister"
            ],
            "description": "GB Persons Of Significant Control Register",
            "url": "http://download.companieshouse.gov.uk/en_pscdata.html",
            "retrievedAt": "2019-07-08T10:37:11Z"
        }
    },
    {
        "statementID": "openownership-register-17401368257004616614",
        "statementType": "entityStatement",
        "entityType": "registeredEntity",
        "name": "INFORMATION AND DATA NETWORKS SUPPLIES HOLDINGS LIMITED",
        "incorporatedInJurisdiction": {
            "name": "United Kingdom of Great Britain and Northern Ireland",
            "code": "GB"
        },
        "identifiers": [
            {
                "scheme": "GB-COH",
                "schemeName": "Companies House",
                "id": "03322263"
            },
            {
                "scheme": "GB-COH",
                "schemeName": "Companies House",
                "id": "03322263"
            },
            {
                "schemeName": "OpenCorporates",
                "id": "https://opencorporates.com/companies/gb/03322263",
                "uri": "https://opencorporates.com/companies/gb/03322263"
            },
            {
                "schemeName": "OpenOwnership Register",
                "id": "http://register.openownership.org/entities/59b95a8f67e4ebf340f09ff8",
                "uri": "http://register.openownership.org/entities/59b95a8f67e4ebf340f09ff8"
            }
        ],
        "foundingDate": "1997-02-21",
        "addresses": [
            {
                "type": "registered",
                "address": "1b Springfield Court, Summerfield Road, Bolton, Lancs, BL3 2NT",
                "country": "GB"
            }
        ]
    }
]