[
    {
        "statementID": "openownership-register-2331071148359961008",
        "statementType": "entityStatement",
        "entityType": "registeredEntity",
        "name": "WARWICKSHIRE COMMUNITY AND VOLUNTARY ACTION",
        "incorporatedInJurisdiction": {
            "name": "United Kingdom of Great Britain and Northern Ireland",
            "code": "GB"
        },
        "identifiers": [
            {
                "scheme": "GB-COH",
                "schemeName": "Companies House",
                "id": "06531268"
            },
            {
                "schemeName": "OpenCorporates",
                "id": "https://opencorporates.com/companies/gb/06531268",
                "uri": "https://opencorporates.com/companies/gb/06531268"
            },
            {
                "schemeName": "OpenOwnership Register",
                "id": "http://register.openownership.org/entities/59b9a0b467e4ebf340234c39",
                "uri": "http://register.openownership.org/entities/59b9a0b467e4ebf340234c39"
            }
        ],
        "foundingDate": "2008-03-11",
        "addresses": [
            {
                "type": "registered",
                "address": "19-20 North Street, Rugby, Warwickshire, CV21 2AG",
                "country": "GB"
            }
        ]
    },
    {
        "statementID": "openownership-register-12660436450687543473",
        "statementType": "ownershipOrControlStatement",
        "statementDate": "2019-09-25",
        "subject": {
            "describedByEntityStatement": "openownership-register-2331071148359961008"
        },
        "interestedParty": {
            "describedByPersonStatement": "openownership-register-16618640580868179535"
        },
        "interests": [
            {
                "type": "influence-or-control",
                "details": "significant-influence-or-control",
                "startDate": "2019-09-25"
            }
        ],
        "source": {
            "type": [
                "officialRegister"
            ],
            "description": "GB Persons Of Significant Control Register",
            "url": "http://download.companieshouse.gov.uk/en_pscdata.html",
            "retrievedAt": "2019-10-16T16:17:08Z"
        }
    },
    {
        "statementID": "openownership-register-10294348812745668795",
        "statementType": "ownershipOrControlStatement",
        "statementDate": "2016-10-31",
        "subject": {
            "describedByEntityStatement": "openownership-register-2331071148359961008"
        },
        "interestedParty": {
            "describedByPersonStatement": "openownership-register-5493782459856237183"
        },
        "interests": [
            {
                "type": "influence-or-control",
                "details": "significant-influence-or-control",
                "startDate": "2016-10-31",
                "endDate": "2017-10-30"
            }
        ],
        "source": {
            "type": [
                "officialRegister"
            ],
            "description": "GB Persons Of Significant Control Register",
            "url": "http://download.companieshouse.gov.uk/en_pscdata.html",
            "retrievedAt": "2019-07-08T10:37:11Z"
        }
    },
    {
        "statementID": "openownership-register-18319200098231144113",
        "statementType": "ownershipOrControlStatement",
        "statementDate": "2018-10-17",
        "subject": {
            "describedByEntityStatement": "openownership-register-2331071148359961008"
        },
        "interestedParty": {
            "describedByPersonStatement": "openownership-register-2891829403239595311"
        },
        "interests": [
            {
                "type": "voting-rights",
                "details": "voting-rights-75-to-100-percent",
                "share": {
                    "minimum": 75,
                    "maximum": 100,
                    "exclusiveMinimum": false,
                    "exclusiveMaximum": false
                },
                "startDate": "2018-10-17",
                "endDate": "2019-09-25"
            }
        ],
        "source": {
            "type": [
                "officialRegister"
            ],
            "description": "GB Persons Of Significant Control Register",
            "url": "http://download.companieshouse.gov.uk/en_pscdata.html",
            "retrievedAt": "2019-10-16T16:17:08Z"
        }
    },
    {
        "statementID": "openownership-register-10388356053988278219",
        "statementType": "ownershipOrControlStatement",
        "statementDate": "2017-10-30",
        "subject": {
            "describedByEntityStatement": "openownership-register-2331071148359961008"
        },
        "interestedParty": {
            "describedByPersonStatement": "openownership-register-5188067166954255667"
        },
        "interests": [
            {
                "type": "influence-or-control",
                "details": "significant-influence-or-control",
                "startDate": "2017-10-30",
                "endDate": "2018-09-27"
            }
        ],
        "source": {
            "type": [
                "officialRegister"
            ],
            "description": "GB Persons Of Significant Control Register",
            "url": "http://download.companieshouse.gov.uk/en_pscdata.html",
            "retrievedAt": "2019-07-08T10:37:11Z"
        }
    },
    {
        "statementID": "openownership-register-16618640580868179535",
        "statementType": "personStatement",
        "personType": "knownPerson",
        "names": [
            {
                "type": "individual",
                "fullName": "Andrew Arnold Gabbitas"
            }
        ],
        "identifiers": [
            {
                "schemeName": "GB Persons Of Significant Control Register",
                "id": "/company/06531268/persons-with-significant-control/individual/PjvAH7wp0b9OSspFNjCm737Baeg"
            },
            {
                "schemeName": "OpenOwnership Register",
                "id": "http://register.openownership.org/entities/5da759e99dfc3fae1831e297",
                "uri": "http://register.openownership.org/entities/5da759e99dfc3fae1831e297"
            }
        ],
        "nationalities": [
            {
                "name": "United Kingdom of Great Britain and Northern Ireland",
                "code": "GB"
            }
        ],
        "birthDate": "1954-09-01",
        "addresses": [
            {
                "address": "19-20, North Street, Rugby, Warwickshire, CV21 2AG"
            }
        ]
    },
    {
        "statementID": "openownership-register-5493782459856237183",
        "statementType": "personStatement",
        "personType": "knownPerson",
        "names": [
            {
                "type": "individual",
                "fullName": "Joanne Audrey Shine"
            }
        ],
        "identifiers": [
            {
                "schemeName": "GB Persons Of Significant Control Register",
                "id": "/company/06531268/persons-with-significant-control/individual/eS2LU3fFsoJzlIhdTPSCb0O09tU"
            },
            {
                "schemeName": "OpenOwnership Register",
                "id": "http://register.openownership.org/entities/59b9a0b467e4ebf340234c41",
                "uri": "http://register.openownership.org/entities/59b9a0b467e4ebf340234c41"
            }
        ],
        "nationalities": [
            {
                "name": "United Kingdom of Great Britain and Northern Ireland",
                "code": "GB"
            }
        ],
        "birthDate": "1951-11-01",
        "addresses": [
            {
                "address": "19-20, North Street, Rugby, Warwickshire, CV21 2AG"
            }
        ]
    },
    {
        "statementID": "openownership-register-2891829403239595311",
        "statementType": "personStatement",
        "personType": "knownPerson",
        "names": [
            {
                "type": "individual",
                "fullName": "Kathleen Elizabeth Harper"
            }
        ],
        "identifiers": [
            {
                "schemeName": "GB Persons Of Significant Control Register",
                "id": "/company/06531268/persons-with-significant-control/individual/nffN7NAU1mypWoS3ztqaPnnSm4g"
            },
            {
                "schemeName": "OpenOwnership Register",
                "id": "http://register.openownership.org/entities/5bcf8c139dfc3fae18cbb484",
                "uri": "http://register.openownership.org/entities/5bcf8c139dfc3fae18cbb484"
            }
        ],
        "nationalities": [
            {
                "name": "United Kingdom of Great Britain and Northern Ireland",
                "code": "GB"
            }
        ],
        "birthDate": "1945-12-01",
        "addresses": [
            {
                "address": "19-20, North Street, Rugby, Warwickshire, CV21 2AG"
            }
        ]
    },
    {
        "statementID": "openownership-register-5188067166954255667",
        "statementType": "personStatement",
        "personType": "knownPerson",
        "names": [
            {
                "type": "individual",
                "fullName": "Judith Mary Morley"
            }
        ],
        "identifiers": [
            {
                "schemeName": "GB Persons Of Significant Control Register",
                "id": "/company/06531268/persons-with-significant-control/individual/rFpxLZtRgc7FOt1dE0GBKAYeySs"
            },
            {
                "schemeName": "OpenOwnership Register",
                "id": "http://register.openownership.org/entities/5ab9fe4d9dfc3fae18363f76",
                "uri": "http://register.openownership.org/entities/5ab9fe4d9dfc3fae18363f76"
            }
        ],
        "nationalities": [
            {
                "name": "United Kingdom of Great Britain and Northern Ireland",
                "code": "GB"
            }
        ],
        "birthDate": "1943-04-01",
        "addresses": [
            {
                "address": "19-20, North Street, Rugby, Warwickshire, CV21 2AG"
            }
        ]
    }
]