{"uri": "https://www.contractsfinder.service.gov.uk/Published/Notice/releases/191fb174-329d-469b-9391-143cb3abeef8.json", "license": "https://www.nationalarchives.gov.uk/doc/open-government-licence/version/2/", "version": "1.1", "releases": [{"id": "ocds-b5fd17-19f021b6-3c51-4d63-b399-3c5c4f20d2c5-346107-eastriding1-dn451299-51652165", "tag": ["tender"], "date": "2019-11-18T00:00:00Z", "ocid": "ocds-b5fd17-19f021b6-3c51-4d63-b399-3c5c4f20d2c5", "buyer": {"id": "bed275928f7af2c565edce04445f0272", "name": "East Riding of Yorkshire"}, "awards": [{"id": "33d28955-5616-4ba7-9756-127ea1a89aa5", "date": "2020-02-25T00:00:00Z", "title": "", "value": {"amount": 142700, "currency": "GBP"}, "status": "active", "suppliers": [{"id": "1", "name": "Bic UK Limited"}, {"id": "2", "name": "Eastpoint"}, {"id": "4", "name": "Newell Rubbermaid UK Limited"}, {"id": "5", "name": "Pentel (Stationery) Ltd"}, {"id": "7", "name": "STAEDTLER (UK) LIMITED"}, {"id": "8", "name": "West Design Products Ltd"}], "description": "See description of related tender", "contractPeriod": {"endDate": "2021-03-31T00:00:00Z", "startDate": "2020-04-01T00:00:00Z"}}], "tender": {"id": "ocds-b5fd17-19f021b6-3c51-4d63-b399-3c5c4f20d2c5-eastriding1-dn451299-51652165", "items": [{"id": 1, "description": "See description of related tender.", "classification": {"id": "30192000", "uri": "http://cpv.data.ac.uk/code-30192000.html", "scheme": "CPV", "description": "Office supplies"}}], "title": "2263-20 Drywipe Pens", "value": {"amount": 0, "currency": "GBP"}, "status": "complete", "minValue": {"amount": 142700, "currency": "GBP"}, "documents": [], "description": "Supply of Drywipe Pens to the East Riding of Yorkshire Council.", "supplyChain": false, "hasEnquiries": null, "tenderPeriod": {"endDate": "2020-01-13T00:00:00Z"}, "awardCriteria": null, "submissionMethod": null, "xClassifications": {"isSuitableForSme": true, "isSuitableForVco": false, "ojeuContractType": "Products"}, "procurementMethod": null, "eligibilityCriteria": null, "awardCriteriaDetails": null, "submissionMethodDetails": null, "procurementMethodDetails": "Restricted procedure", "procurementMethodRationale": "", "numberOfTenderers": 6, "tenderers": [{"id": "1", "name": "Bic UK Limited"}, {"id": "2", "name": "Eastpoint"}, {"id": "4", "name": "Newell Rubbermaid UK Limited"}, {"id": "5", "name": "Pentel (Stationery) Ltd"}, {"id": "7", "name": "STAEDTLER (UK) LIMITED"}, {"id": "8", "name": "West Design Products Ltd"}], "contractPeriod": {"startDate": "2020-04-01T00:00:00Z", "endDate": "2021-03-31T00:00:00Z"}}, "parties": [{"id": "bed275928f7af2c565edce04445f0272", "name": "East Riding of Yorkshire", "roles": ["buyer"], "address": {"region": null, "locality": "Beverley", "postalCode": "HU17 9BA", "countryName": "England", "streetAddress": "County Hall Cross Street"}, "contactPoint": {"uri": "http://www.eastriding.gov.uk", "name": "Mirheta Huremovic", "email": "mirheta.huremovic@eastriding.gov.uk", "faxNumber": null, "telephone": "+44 1482395336"}}, {"id": "1", "sme": false, "vco": false, "name": "Bic UK Limited", "roles": ["supplier", "tenderer"], "address": {"region": "", "locality": "", "postalCode": "", "countryName": "", "streetAddress": "BIC, Chaplin House, Widewater Place, Moorhall Road, Harefield, Middlesex, UB9 6NS"}, "identifier": {"id": "00389090", "scheme": "GB-COH", "legalName": "BIC U.K. LIMITED"}, "contactPoint": {"name": "", "email": "", "faxNumber": "", "telephone": ""}, "x_awardValue": {"amount": null, "currency": "GBP"}}, {"id": "2", "sme": false, "vco": false, "name": "Eastpoint", "roles": ["supplier", "tenderer"], "address": {"region": "", "locality": "", "postalCode": "", "countryName": "", "streetAddress": "Eastpoint\nThe Old Coachworks\nRotterdam Road\nLowestoft\nSuffolk\nNR32 2EX"}, "identifier": {"id": "08106805", "scheme": "GB-COH", "legalName": "EASTPOINT ASSET LTD"}, "contactPoint": {"name": "", "email": "", "faxNumber": "", "telephone": ""}, "x_awardValue": {"amount": null, "currency": "GBP"}}, {"id": "4", "sme": false, "vco": false, "name": "Newell Rubbermaid UK Limited", "roles": ["supplier", "tenderer"], "address": {"region": "", "locality": "", "postalCode": "", "countryName": "", "streetAddress": "Newell Brands\nHalifax Avenue\nFradley\nLichfield\nStaffordshire\nWS13 8SS"}, "identifier": {"id": "00104102", "scheme": "GB-COH", "legalName": "NEWELL RUBBERMAID UK LIMITED"}, "contactPoint": {"name": "", "email": "", "faxNumber": "", "telephone": ""}, "x_awardValue": {"amount": null, "currency": "GBP"}}, {"id": "5", "sme": false, "vco": false, "name": "Pentel (Stationery) Ltd", "roles": ["supplier", "tenderer"], "address": {"region": "", "locality": "", "postalCode": "", "countryName": "", "streetAddress": "Pentel (Stationery) Limited\nHunts Rise\nSouth Marston  Park\nSwindon\nWiltshire\nSN3 4TW"}, "identifier": {"id": "00997644", "scheme": "GB-COH", "legalName": "PENTEL (STATIONERY) LIMITED"}, "contactPoint": {"name": "", "email": "", "faxNumber": "", "telephone": ""}, "x_awardValue": {"amount": null, "currency": "GBP"}}, {"id": "7", "sme": false, "vco": false, "name": "STAEDTLER (UK) LIMITED", "roles": ["supplier", "tenderer"], "address": {"region": "", "locality": "", "postalCode": "", "countryName": "", "streetAddress": "Staedtler (UK) Limited \n31 Old Field Road \nBocam Park\nPencoed, Bridgend\nSouth Wales \nCF35 5LJ"}, "identifier": {"id": "00797272", "scheme": "GB-COH", "legalName": "STAEDTLER (U.K.) LIMITED"}, "contactPoint": {"name": "", "email": "", "faxNumber": "", "telephone": ""}, "x_awardValue": {"amount": null, "currency": "GBP"}}, {"id": "8", "sme": false, "vco": false, "name": "West Design Products Ltd", "roles": ["supplier", "tenderer"], "address": {"region": "", "locality": "", "postalCode": "", "countryName": "", "streetAddress": "WestHouse \nShearway Business Par \nPent Road\nFolkestone\nKent \nCT19 4RJ"}, "identifier": {"id": "02723202", "scheme": "GB-COH", "legalName": "WEST DESIGN PRODUCTS LIMITED"}, "contactPoint": {"name": "", "email": "", "faxNumber": "", "telephone": ""}, "x_awardValue": {"amount": null, "currency": "GBP"}}], "language": "en-GB", "initiationType": "tender"}], "publisher": {"uid": null, "uri": "https://www.contractsfinder.service.gov.uk", "name": "DUE NORTH LIMITED", "scheme": "GB-GOVUK-crown_comercial_service"}, "extensions": ["https://raw.githubusercontent.com/open-contracting/ocds_process_title_extension/v1.1/extension.json"], "publishedDate": "2020-02-26T09:03:32Z", "publicationPolicy": "https://www.gov.uk/government/publications/open-contracting"}