{"uri": "https://www.contractsfinder.service.gov.uk/Published/Notice/releases/1177aa64-e5d5-498c-af96-92ff0bc40d75.json", "license": "https://www.nationalarchives.gov.uk/doc/open-government-licence/version/2/", "version": "1.1", "releases": [{"id": "ocds-b5fd17-0245cc95-f843-4803-acb7-3bfb1314707f-348114-bip84278501", "tag": ["tender"], "date": "2020-01-17T00:00:00Z", "ocid": "ocds-b5fd17-0245cc95-f843-4803-acb7-3bfb1314707f", "buyer": {"id": "f27d44abbdd6a50eac25b233cca25b44", "name": "Ministry of Defence, Ships, Maritime Platform Systems (MPS)"}, "awards": [{"id": "cd2ae4b1-f63a-4bfe-b827-f57f83527227", "date": "2020-02-14T00:00:00Z", "title": "", "value": {"amount": 260633.18, "currency": "GBP"}, "status": "active", "suppliers": [{"id": "1", "name": "Ridgeway Components"}, {"id": "2", "name": "Cyclops Electronics Ltd"}, {"id": "3", "name": "Oracle Components Ltd"}], "description": "See description of related tender", "contractPeriod": {"endDate": "2021-04-16T00:00:00Z", "startDate": "2020-02-16T00:00:00Z"}}], "tender": {"id": "ocds-b5fd17-0245cc95-f843-4803-acb7-3bfb1314707f-bip84278501", "items": [{"id": 1, "description": "See description of related tender.", "classification": {"id": "35500000", "uri": "http://cpv.data.ac.uk/code-35500000.html", "scheme": "CPV", "description": "Warships and associated parts"}}], "title": "MSCIP Lot 39", "value": {"amount": 0, "currency": "GBP"}, "status": "complete", "minValue": {"amount": 260633, "currency": "GBP"}, "documents": [], "description": "Supply of general naval stores - Marine Electrical", "supplyChain": false, "hasEnquiries": null, "tenderPeriod": {"endDate": "2020-02-14T00:00:00Z"}, "awardCriteria": null, "submissionMethod": null, "xClassifications": {"isSuitableForSme": true, "isSuitableForVco": false, "ojeuContractType": "Products"}, "procurementMethod": null, "eligibilityCriteria": null, "awardCriteriaDetails": null, "submissionMethodDetails": null, "procurementMethodDetails": "Open procedure", "procurementMethodRationale": "", "numberOfTenderers": 3, "tenderers": [{"id": "1", "name": "Ridgeway Components"}, {"id": "2", "name": "Cyclops Electronics Ltd"}, {"id": "3", "name": "Oracle Components Ltd"}], "contractPeriod": {"startDate": "2020-02-16T00:00:00Z", "endDate": "2021-04-16T00:00:00Z"}}, "parties": [{"id": "f27d44abbdd6a50eac25b233cca25b44", "name": "Ministry of Defence, Ships, Maritime Platform Systems (MPS)", "roles": ["buyer"], "address": {"region": null, "locality": "Bristol", "postalCode": "BS348JH", "countryName": "UK", "streetAddress": "The Tender Board, Defence Equipment and Support Commercial, The Central Gatehouse MOD, Abbey Wood South"}, "contactPoint": {"name": "", "email": "amy.abbott106@mod.gov.uk", "faxNumber": null, "telephone": "+443067988816"}}, {"id": "1", "sme": false, "vco": false, "name": "Ridgeway Components", "roles": ["supplier", "tenderer"], "address": {"region": "", "locality": "", "postalCode": "", "countryName": "", "streetAddress": "Unit 5, Prosperity Way, Middlewich\n        Cheshire\n        CW10 0GD"}, "identifier": {"id": "", "uri": null, "scheme": "", "legalName": null}, "contactPoint": {"name": "", "email": "", "faxNumber": "", "telephone": ""}, "x_awardValue": {"amount": null, "currency": "GBP"}}, {"id": "2", "sme": false, "vco": false, "name": "Cyclops Electronics Ltd", "roles": ["supplier", "tenderer"], "address": {"region": "", "locality": "", "postalCode": "", "countryName": "", "streetAddress": "Cyclops House\n        Link Business Park\n        York\n        YO10 3JB"}, "identifier": {"id": "", "uri": null, "scheme": "", "legalName": null}, "contactPoint": {"name": "", "email": "", "faxNumber": "", "telephone": ""}, "x_awardValue": {"amount": null, "currency": "GBP"}}, {"id": "3", "sme": false, "vco": false, "name": "Oracle Components Ltd", "roles": ["supplier", "tenderer"], "address": {"region": "", "locality": "", "postalCode": "", "countryName": "", "streetAddress": "3 The Fairway\n        Bushfair\n        Harlow\n        Essex\n        CM18 6LY"}, "identifier": {"id": "05045250", "scheme": "GB-COH", "legalName": "ORACLECOMPONENTS LTD"}, "contactPoint": {"name": "", "email": "", "faxNumber": "", "telephone": ""}, "x_awardValue": {"amount": null, "currency": "GBP"}}], "language": "en-GB", "initiationType": "tender"}], "publisher": {"uid": null, "uri": "https://www.contractsfinder.service.gov.uk", "name": "BIP SOLUTIONS LIMITED", "scheme": "GB-GOVUK-crown_comercial_service"}, "extensions": ["https://raw.githubusercontent.com/open-contracting/ocds_process_title_extension/v1.1/extension.json"], "publishedDate": "2020-03-06T07:00:56Z", "publicationPolicy": "https://www.gov.uk/government/publications/open-contracting"}