{"uri": "https://www.contractsfinder.service.gov.uk/Published/Notice/releases/ce0f2c39-a8ea-4ad9-bf43-fdbd8a7ad7fe.json", "license": "https://www.nationalarchives.gov.uk/doc/open-government-licence/version/2/", "version": "1.1", "releases": [{"id": "ocds-b5fd17-16c02c4d-99b2-461b-8e6e-e31e22ff7e3d-359157-lgss001-dn453191-09747886", "tag": ["tender"], "date": "2020-01-29T00:00:00Z", "ocid": "ocds-b5fd17-16c02c4d-99b2-461b-8e6e-e31e22ff7e3d", "buyer": {"id": "12eb780fdf534e9bc2f81b5532e5d394", "name": "Cambridgeshire County Council"}, "awards": [{"id": "e27b9353-b987-43f6-9551-a0bf2c2f5ef3", "date": "2020-05-05T00:00:00Z", "value": {"amount": 14393173, "currency": "GBP"}, "status": "active", "suppliers": [{"id": "1", "name": "Everyone Health Ltd"}, {"id": "2", "name": "Everyone Health Ltd"}, {"id": "3", "name": "Cambridge City Council"}], "description": "See description of related tender", "contractPeriod": {"endDate": "2025-05-31T00:00:00Z", "startDate": "2020-06-01T00:00:00Z"}}], "tender": {"id": "ocds-b5fd17-16c02c4d-99b2-461b-8e6e-e31e22ff7e3d-lgss001-dn453191-09747886", "items": [{"id": 1, "description": "See description of related tender.", "classification": {"id": "85000000", "uri": "http://cpv.data.ac.uk/code-85000000.html", "scheme": "CPV", "description": "Health and social work services"}}], "title": "Cambridgeshire and Peterborough Integrated Lifestyle Service", "value": {"currency": "GBP"}, "status": "complete", "minValue": {"amount": 14393173, "currency": "GBP"}, "description": "Cambridgeshire County Council and Peterborough City Council are commissioning an Integrated Lifestyle Service, bringing together a number of services that focus on promoting the adoption of healthy lifestyle behaviours and the prevention of associated poor health outcomes at universal and individual levels.\r\nThe procurement is divided into three lots:\r\n1) Core Integrated Lifestyle services - place based lifestyle interventions that includes range of generic and specialist health trainers, family and tier 2 weight management services, outreach NHS Health Checks, National Child Measurement Programme and behavioural change training.\r\n2) Tier 3 Adult Weight Management - Specialist intensive adult weight management services.\r\n3) Tier 1 Lifestyle Services - includes universal approaches with whole population-wide services and initiatives along with targeted interventions. The service is focused upon prevention and early intervention to secure improvements in health outcomes.", "tenderPeriod": {"endDate": "2020-02-05T00:00:00Z"}, "xClassifications": {"isSuitableForSme": true, "isSuitableForVco": true, "ojeuContractType": "Services"}, "procurementMethodDetails": "Negotiated procedure", "numberOfTenderers": 3, "tenderers": [{"id": "1", "name": "Everyone Health Ltd"}, {"id": "2", "name": "Everyone Health Ltd"}, {"id": "3", "name": "Cambridge City Council"}], "contractPeriod": {"startDate": "2020-06-01T00:00:00Z", "endDate": "2025-05-31T00:00:00Z"}}, "parties": [{"id": "12eb780fdf534e9bc2f81b5532e5d394", "name": "Cambridgeshire County Council", "roles": ["buyer"], "address": {"locality": "Cambridge", "postalCode": "CB3 0AP", "countryName": "England", "streetAddress": "Shire Hall Castle Hill"}, "contactPoint": {"email": "sarah.fuller@cambridgeshire.gov.uk"}}, {"id": "1", "name": "Everyone Health Ltd", "roles": ["supplier", "tenderer"], "address": {"streetAddress": "3 Watling Drive, Hinckley, Leicestershire, LE10 3EY, United Kingdom \n"}, "identifier": {"id": ""}, "contactPoint": {}, "x_awardValue": {"currency": "GBP"}}, {"id": "2", "name": "Everyone Health Ltd", "roles": ["supplier", "tenderer"], "address": {"streetAddress": "3 Watling Drive, Hinckley, Leicestershire, LE10 3EY, United Kingdom \n"}, "identifier": {"id": ""}, "contactPoint": {}, "x_awardValue": {"currency": "GBP"}}, {"id": "3", "name": "Cambridge City Council", "roles": ["supplier", "tenderer"], "address": {"streetAddress": "116 Chesterton Rd, Cambridge, Cambridgeshire, CB4 1BZ, United Kingdom"}, "identifier": {"id": ""}, "contactPoint": {}, "x_awardValue": {"currency": "GBP"}}], "language": "en-GB", "initiationType": "tender"}], "publisher": {"uri": "https://www.contractsfinder.service.gov.uk", "name": "DUE NORTH LIMITED", "scheme": "GB-GOVUK-crown_comercial_service"}, "extensions": ["https://raw.githubusercontent.com/open-contracting/ocds_process_title_extension/v1.1/extension.json"], "publishedDate": "2020-05-15T09:50:18Z", "publicationPolicy": "https://www.gov.uk/government/publications/open-contracting"}